Workbook

Sheet Summary
A1: FDIC comparison — your bank list vs FDIC BankFind
A2: Source: banks.data.fdic.gov API, pulled 2026-07-03 (financials as of 3/31/2026). Matched by FDIC cert number — no name guessing.
A4: Banks checked | B4: 426
A5: Closed or merged (no longer FDIC-insured) | B5: =COUNTA('Closed or merged'!A:A)-1
A6: Name changed | B6: =COUNTA('Name changes'!A:A)-1
A7: Websites on file | B7: =COUNTA(Websites!A:A)-1
A8: Websites that failed to load | B8: =COUNTIF(Websites!E:E,"NO")
A9: Banks with refreshed asset figures | B9: =COUNTA(Assets!A:A)-1
A11: Notes
A12: • Every row is matched by cert number, so a wrong-bank mixup is impossible.
A13: • Websites are what each bank filed with the FDIC; the Loads? column is a live check from today.
A14: • 'Closed or merged' banks may have been acquired — accounts there usually moved to the successor bank.

Sheet Closed or merged
A1: Cert | B1: Bank (your list) | C1: State | D1: No longer FDIC-insured since | E1: What to do
A2: 32306 | B2: New Foundation Savings Bank | C2: OH | D2: 06/01/2026 | E2: Merged, converted, or closed — check where accounts went; remove or retag in the app
A3: 90146 | B3: Athol Savings Bank | C3: MA | D3: 01/01/2026 | E3: Merged, converted, or closed — check where accounts went; remove or retag in the app
A4: 28481 | B4: Colonial Federal Savings Bank | C4: MA | D4: 11/01/2025 | E4: Merged, converted, or closed — check where accounts went; remove or retag in the app
A5: 30492 | B5: Jackson Federal Savings and Loan Association | C5: MN | D5: 08/27/2025 | E5: Merged, converted, or closed — check where accounts went; remove or retag in the app
A6: 28167 | B6: Eastern Connecticut Savings Bank | C6: CT | D6: 07/01/2025 | E6: Merged, converted, or closed — check where accounts went; remove or retag in the app
A7: 26516 | B7: Wakefield Co-operative Bank | C7: MA | D7: 05/01/2025 | E7: Merged, converted, or closed — check where accounts went; remove or retag in the app
A8: 29875 | B8: NVE Bank | C8: NJ | D8: 04/28/2025 | E8: Merged, converted, or closed — check where accounts went; remove or retag in the app
A9: 28611 | B9: Pulaski Savings Bank | C9: IL | D9: 01/17/2025 | E9: Merged, converted, or closed — check where accounts went; remove or retag in the app
A10: 17748 | B10: Gorham Savings Bank | C10: ME | D10: 01/01/2025 | E10: Merged, converted, or closed — check where accounts went; remove or retag in the app
A11: 29986 | B11: Guardian Savings Bank | C11: IL | D11: 11/29/2024 | E11: Merged, converted, or closed — check where accounts went; remove or retag in the app
A12: 30519 | B12: Freehold Bank | C12: NJ | D12: 10/05/2024 | E12: Merged, converted, or closed — check where accounts went; remove or retag in the app
A13: 57849 | B13: Pioneer Commercial Bank | C13: NY | D13: 10/01/2024 | E13: Merged, converted, or closed — check where accounts went; remove or retag in the app
... A22: 29646 | B22: First Federal Savings and Loan Association | C22: MS | D22: 07/01/2023 | E22: Merged, converted, or closed — check where accounts went; remove or retag in the app

Sheet Name changes
A1: Cert | B1: Name in your list | C1: Current FDIC name | D1: State
A2: 15912 | B2: Savings Bank of Danbury | C2: Ives Bank | D2: CT
A3: 17262 | B3: Essex Savings Bank | C3: Essex Bank | D3: CT
A4: 18194 | B4: The Guilford Savings Bank | C4: Ascend Bank | D4: CT
A5: 20741 | B5: Pioneer Bank | C5: Pioneer Bank, National Association | D5: NY
A6: 26484 | B6: North Shore Bank, a Co-operative Bank | C6: TruNorth Bank | D6: MA
A7: 26517 | B7: Cape Cod Co-operative Bank | C7: Cape & Coast Bank | D7: MA
A8: 26523 | B8: Hometown Bank | C8: Bankhometown | D8: MA
A9: 28266 | B9: Raymond Federal Bank | C9: Connect Community Bank | D9: WA
A10: 28778 | B10: Somerset Savings Bank, SLA | C10: Somerset Regal Bank | D10: NJ
A11: 28780 | B11: Arundel Federal Savings Bank | C11: Arundel Bank | D11: MD
A12: 28949 | B12: Amory Federal Savings and Loan Association | C12: Amory First Savings And Loan Bank, Ssb | D12: MS
A13: 29496 | B13: Seneca Savings | C13: Seneca Savings Bank, National Association | D13: NY
... A21: 90188 | B21: Easthampton Savings Bank | C21: Bankesb | D21: MA

Sheet Websites
A1: Cert | B1: Bank | C1: State | D1: Website (per FDIC filing) | E1: Loads?
A2: 15990 | B2: Watertown Savings Bank | C2: NY | D2: www.watersavingsbank.com | E2: NO
A3: 17749 | B3: Bath Savings Institution | C3: ME | D3: www.bathsavings.bank | E3: NO
A4: 18204 | B4: First County Bank | C4: CT | D4: www.firstcountybank.com | E4: NO
A5: 27678 | B5: First Federal Community Bank, SSB | C5: TX | D5: www.ffcbank.com | E5: NO
A6: 27727 | B6: Lyons Federal Bank | C6: KS | D6: WWW.LYONSFED.COM | E6: NO
A7: 28157 | B7: The Cincinnatus Savings & Loan Co. | C7: OH | D7: www.cincinnatussl.com | E7: NO
A8: 28480 | B8: Columbia Savings and Loan Association | C8: WI | D8: www.columbiasla.com | E8: NO
A9: 28836 | B9: United Savings Bank | C9: PA | D9: HTTPS://WWW.UNITEDSAVINGSBANK.COM | E9: NO
A10: 29627 | B10: Second Federal Savings and Loan Association of Philadelphia | C10: PA | D10: www.secondfed.com | E10: NO
A11: 29672 | B11: cfsbank | C11: PA | D11: www.cfsbank.bank | E11: NO
A12: 31197 | B12: First Federal Savings and Loan Association | C12: KY | D12: www.firstfederalhazard.com | E12: NO
A13: 12013 | B13: Union County Savings Bank | C13: NJ | D13: www.unioncountysavings.com | E13: yes
... A396: 90311 | B396: Bay State Savings Bank | C396: MA | D396: baystatesavingsbank.com | E396: yes

Sheet Assets
A1: Cert | B1: Bank | C1: Assets in app ($000, 2023) | D1: FDIC assets ($000, 3/31/2026) | E1: Change
A2: 12013 | B2: Union County Savings Bank | C2: 1820867 | D2: 1490109 | E2: =IF(C2=0,"",(D2-C2)/C2)
A3: 13063 | B3: Kennebunk Savings Bank | C3: 1846791 | D3: 2099477 | E3: =IF(C3=0,"",(D3-C3)/C3)
A4: 14134 | B4: Passumpsic Savings Bank | C4: 838127 | D4: 925377 | E4: =IF(C4=0,"",(D4-C4)/C4)
A5: 14136 | B5: Wells River Savings Bank | C5: 228201 | D5: 259539 | E5: =IF(C5=0,"",(D5-C5)/C5)
A6: 14140 | B6: Northfield Savings Bank | C6: 1414255 | D6: 1576055 | E6: =IF(C6=0,"",(D6-C6)/C6)
A7: 15912 | B7: Savings Bank of Danbury | C7: 1438145 | D7: 1694155 | E7: =IF(C7=0,"",(D7-C7)/C7)
A8: 15966 | B8: Fulton Savings Bank | C8: 475722 | D8: 493036 | E8: =IF(C8=0,"",(D8-C8)/C8)
A9: 15969 | B9: Rondout Savings Bank | C9: 524847 | D9: 510424 | E9: =IF(C9=0,"",(D9-C9)/C9)
A10: 15970 | B10: Ulster Savings Bank | C10: 1247761 | D10: 1371883 | E10: =IF(C10=0,"",(D10-C10)/C10)
A11: 15987 | B11: Walden Savings Bank | C11: 736016 | D11: 977293 | E11: =IF(C11=0,"",(D11-C11)/C11)
A12: 15990 | B12: Watertown Savings Bank | C12: 923496 | D12: 970247 | E12: =IF(C12=0,"",(D12-C12)/C12)
A13: 16026 | B13: Ridgewood Savings Bank | C13: 6834299 | D13: 7540183 | E13: =IF(C13=0,"",(D13-C13)/C13)
... A406: 90311 | B406: Bay State Savings Bank | C406: 500594 | D406: 585390 | E406: =IF(C406=0,"",(D406-C406)/C406)

Sheet City changes
A1: Cert | B1: Bank | C1: City in your list | D1: FDIC city
A2: 14134 | B2: Passumpsic Savings Bank | C2: ST. JOHNSBURY | D2: Saint Johnsbury
A3: 17741 | B3: Maine Community Bank | C3: BIDDEFORD | D3: Portland
A4: 18238 | B4: Chelsea Groton Bank | C4: NORWICH | D4: Groton
A5: 23287 | B5: The Cape Cod Five Cents Savings Bank | C5: ORLEANS | D5: Hyannis
A6: 26336 | B6: The Village Bank | C6: AUBURNDALE | D6: Newton
